odoo/addons/theme_light/README.rst
odoo/addons/theme_light/__init__.py
odoo/addons/theme_light/__manifest__.py
odoo/addons/theme_light/i18n/theme_light.pot
odoo/addons/theme_light/readme/CONTRIBUTORS.rst
odoo/addons/theme_light/readme/DESCRIPTION.rst
odoo/addons/theme_light/report/header_report_G002.xml
odoo/addons/theme_light/static/css/bootstrap.css
odoo/addons/theme_light/static/css/global_theme.css
odoo/addons/theme_light/static/css/global_theme.sass
odoo/addons/theme_light/static/css/invoice_B001.css
odoo/addons/theme_light/static/css/invoice_B002.css
odoo/addons/theme_light/static/css/invoice_G001.css
odoo/addons/theme_light/static/css/invoice_G002.css
odoo/addons/theme_light/static/css/invoice_O002.css
odoo/addons/theme_light/static/css/invoice_P002.css
odoo/addons/theme_light/static/css/invoice_orange.css
odoo/addons/theme_light/static/css/mail_template_B001.css
odoo/addons/theme_light/static/css/theme_zen_black.css
odoo/addons/theme_light/static/css/theme_zen_blue.css
odoo/addons/theme_light/static/css/theme_zen_brown.css
odoo/addons/theme_light/static/css/theme_zen_green.css
odoo/addons/theme_light/static/css/theme_zen_orange.css
odoo/addons/theme_light/static/css/theme_zen_purple.css
odoo/addons/theme_light/static/css/theme_zen_red.css
odoo/addons/theme_light/static/css/theme_zen_yellow.css
odoo/addons/theme_light/static/description/index.html
odoo/addons/theme_light/static/font/BEBASNEUE_BOLD.ttf
odoo/addons/theme_light/static/font/ErbarreBold.ttf
odoo/addons/theme_light/static/font/Lato-Bold.ttf
odoo/addons/theme_light/static/font/Lato-Italic.ttf
odoo/addons/theme_light/static/font/Lato-Regular.ttf
odoo/addons/theme_light/static/font/Montserrat-Bold.ttf
odoo/addons/theme_light/static/font/Montserrat-Regular.ttf
odoo/addons/theme_light/static/font/Roboto-Bold.ttf
odoo/addons/theme_light/static/font/Roboto-Regular.ttf
odoo/addons/theme_light/static/font/centuryschl-roma-webfont.ttf
odoo/addons/theme_light/static/img/gallery/arrow_bleu_img.jpg
odoo12_addon_theme_light-12.0.1.0.0.99.dev10.dist-info/METADATA
odoo12_addon_theme_light-12.0.1.0.0.99.dev10.dist-info/WHEEL
odoo12_addon_theme_light-12.0.1.0.0.99.dev10.dist-info/top_level.txt
odoo12_addon_theme_light-12.0.1.0.0.99.dev10.dist-info/RECORD
